LICENSE
MANIFEST.in
README.md
setup.py
django_tranlation_sanitizer.egg-info/PKG-INFO
django_tranlation_sanitizer.egg-info/SOURCES.txt
django_tranlation_sanitizer.egg-info/dependency_links.txt
django_tranlation_sanitizer.egg-info/top_level.txt
translation_sanitizer/__init__.py
translation_sanitizer/apps.py
translation_sanitizer/management/commands/makemessages.py