Metadata-Version: 2.1
Name: django-tranlation-sanitizer
Version: 0.1
Summary: A simple Django app to sanitize the output of makemessages command.
Home-page: https://github.com/24htv/django-translation-sanitizer
Author: Dmitry Arkhipenko
Author-email: dk.dev@pm.me
License: BSD 2-Clause License
Platform: UNKNOWN
Classifier: Environment :: Web Environment
Classifier: Framework :: Django
Classifier: Framework :: Django :: 1.11
Classifier: Framework :: Django :: 2.0
Classifier: Framework :: Django :: 2.1
Classifier: Framework :: Django :: 2.2
Classifier: Intended Audience :: Developers
Classifier: License :: OSI Approved :: BSD License
Classifier: Operating System :: OS Independent
Classifier: Programming Language :: Python
Classifier: Programming Language :: Python :: 3.5
Classifier: Programming Language :: Python :: 3.6
Classifier: Topic :: Internet :: WWW/HTTP
Classifier: Topic :: Internet :: WWW/HTTP :: Dynamic Content
